pysqream/__init__.py
pysqream/casting.py
pysqream/column_buffer.py
pysqream/connection.py
pysqream/cursor.py
pysqream/globals.py
pysqream/logger.py
pysqream/ping.py
pysqream/pysqream.py
pysqream/type_mapper.py
pysqream/utils.py
pysqream/column_packers/__init__.py
pysqream/column_packers/column_packer.py
pysqream/column_packers/packer_factory.py
pysqream/column_packers/array_packers/__init__.py
pysqream/column_packers/array_packers/array_packer.py
pysqream/column_packers/array_packers/numpy_array_packer.py
pysqream/column_packers/chars_packers/__init__.py
pysqream/column_packers/chars_packers/blob_packer.py
pysqream/column_packers/chars_packers/varchar_packer.py
pysqream/column_packers/date_packers/__init__.py
pysqream/column_packers/date_packers/abstract_date_packer.py
pysqream/column_packers/date_packers/date_packer.py
pysqream/column_packers/date_packers/datetime_packer.py
pysqream/column_packers/date_packers/timestamptz_packer.py
pysqream/column_packers/number_packers/__init__.py
pysqream/column_packers/number_packers/decimal_packer.py
pysqream/column_packers/number_packers/number_packer.py
pysqream/server/__init__.py
pysqream/server/connection_params.py
pysqream/server/sqclient.py
pysqream/server/sqsocket.py
pysqream-6.3.0.dist-info/licenses/LICENSE
tests/__init__.py
tests/conftest.py
tests/is_commit_covered.py
tests/mock.py
tests/pytest_logger.py
tests/test_base.py
tests/utils.py
tests/array_tests/__init__.py
tests/array_tests/test_allow_array.py
tests/array_tests/test_array_extractor.py
tests/array_tests/test_array_network_insert.py
tests/big_data_tests/__init__.py
tests/big_data_tests/test_big_data.py
tests/parameterized_tests/__init__.py
tests/parameterized_tests/test_parameterized_statements.py
tests/sanity_tests/__init__.py
tests/sanity_tests/test_connection.py
tests/sanity_tests/test_cursor.py
tests/sanity_tests/test_fetch.py
tests/sanity_tests/test_negative.py
tests/sanity_tests/test_positive.py
tests/sanity_tests/test_threads.py
tests/unit_tests/__init__.py
tests/unit_tests/mocks.py
pysqream-6.3.0.dist-info/METADATA
pysqream-6.3.0.dist-info/WHEEL
pysqream-6.3.0.dist-info/top_level.txt
pysqream-6.3.0.dist-info/RECORD
