Metadata-Version: 2.4
Name: pysqream
Version: 6.3.0
Summary: DB-API connector for SQream DB
Home-page: https://github.com/SQream/pysqream
Author: SQream
Author-email: info@sqream.com
Keywords: database db-api sqream sqreamdb
Classifier: Programming Language :: Python :: 3.9
Classifier: License :: OSI Approved :: BSD License
Classifier: Operating System :: OS Independent
Requires-Python: >=3.9,<=3.13.1
License-File: LICENSE
Requires-Dist: numpy<=2.3.0
Requires-Dist: packaging<=25.0
Requires-Dist: pyarrow<=20.0.0
Requires-Dist: pandas<=2.3.0
Requires-Dist: Faker<=37.3.0
Requires-Dist: numexpr<=2.10.2
Requires-Dist: setuptools-scm==8.3.1
Dynamic: author
Dynamic: author-email
Dynamic: classifier
Dynamic: description
Dynamic: home-page
Dynamic: keywords
Dynamic: license-file
Dynamic: requires-dist
Dynamic: requires-python
Dynamic: summary
